AUTHORS.rst
CHANGELOG.rst
LICENSE
MANIFEST.in
README.rst
setup.py
foundry/__init__.py
foundry/admin.py
foundry/admin_forms.py
foundry/admin_views.py
foundry/ambientmobile.py
foundry/api.py
foundry/backends.py
foundry/context_processors.py
foundry/decorators.py
foundry/eventhandlers.py
foundry/feeds.py
foundry/forms.py
foundry/interfaces.py
foundry/managers.py
foundry/middleware.py
foundry/mixins.py
foundry/models.py
foundry/monkey.py
foundry/profile_models.py
foundry/settings.py
foundry/settings_dev.py
foundry/tasks.py
foundry/urls.py
foundry/utils.py
foundry/views.py
foundry/widgets.py
foundry/fixtures/countries.json
foundry/fixtures/photosizes.json
foundry/locale/af/LC_MESSAGES/django.mo
foundry/locale/af/LC_MESSAGES/django.po
foundry/locale/fr/LC_MESSAGES/django.mo
foundry/locale/fr/LC_MESSAGES/django.po
foundry/management/__init__.py
foundry/management/__init__.pyc
foundry/management/commands/__init__.py
foundry/management/commands/__init__.pyc
foundry/management/commands/load_photosizes.py
foundry/management/commands/load_photosizes.pyc
foundry/management/commands/report_naughty_words.py
foundry/migrations/0001_initial.py
foundry/migrations/0001_initial.pyc
foundry/migrations/0002_auto__del_field_listing_display_primary_category__add_field_listing_di.py
foundry/migrations/0002_auto__del_field_listing_display_primary_category__add_field_listing_di.pyc
foundry/migrations/0003_auto__add_chatroom__del_field_listing_display_category.py
foundry/migrations/0003_auto__add_chatroom__del_field_listing_display_category.pyc
foundry/migrations/0004_auto__del_chatroom.py
foundry/migrations/0004_auto__del_chatroom.pyc
foundry/migrations/0005_auto__add_chatroom.py
foundry/migrations/0005_auto__add_chatroom.pyc
foundry/migrations/0006_auto__add_blogpost.py
foundry/migrations/0006_auto__add_blogpost.pyc
foundry/migrations/0007_auto__add_field_blogpost_content.py
foundry/migrations/0007_auto__add_field_blogpost_content.pyc
foundry/migrations/0008_auto.py
jmbo_foundry.egg-info/PKG-INFO
jmbo_foundry.egg-info/SOURCES.txt
jmbo_foundry.egg-info/dependency_links.txt
jmbo_foundry.egg-info/not-zip-safe
jmbo_foundry.egg-info/requires.txt
jmbo_foundry.egg-info/top_level.txt