Metadata-Version: 1.1
Name: jmbo-foundry
Version: 2.1.3
Summary: Jmbo Foundry ties together the various Jmbo products enabling you to rapidly build multilingual web and mobi sites with the minimum amount of code and customization.
Home-page: http://github.com/praekelt/jmbo-foundry
Author: Praekelt Foundation
Author-email: dev@praekelt.com
License: BSD
Platform: UNKNOWN
Classifier: Programming Language :: Python
Classifier: License :: OSI Approved :: BSD License
Classifier: Development Status :: 4 - Beta
Classifier: Operating System :: OS Independent
Classifier: Framework :: Django
Classifier: Intended Audience :: Developers
Classifier: Topic :: Internet :: WWW/HTTP :: Dynamic Content
